dataclass_persistence/__init__.py
dataclass_persistence/core.py
dataclass_persistence-0.3.7.dist-info/LICENSE
dataclass_persistence-0.3.7.dist-info/METADATA
dataclass_persistence-0.3.7.dist-info/WHEEL
dataclass_persistence-0.3.7.dist-info/top_level.txt
dataclass_persistence-0.3.7.dist-info/RECORD
