Metadata-Version: 2.1
Name: dataclass-persistence
Version: 0.3.7
Summary: Persists information contained in dataclasses.
Home-page: https://github.com/philipp-mohr/dataclass-persistence
Author: P.Mohr
Author-email: philipp.mohr@tuhh.de
License: MIT
Classifier: License :: OSI Approved :: MIT License
Classifier: Programming Language :: Python
Classifier: Programming Language :: Python :: 3.8
Classifier: Programming Language :: Python :: Implementation :: CPython
Classifier: Programming Language :: Python :: Implementation :: PyPy
Requires-Python: >=3.10.0
License-File: LICENSE
Requires-Dist: numpy
Requires-Dist: StrEnum
Provides-Extra: dev
Requires-Dist: pytest ; extra == 'dev'
Requires-Dist: check-manifest ; extra == 'dev'
Requires-Dist: twine ; extra == 'dev'
Requires-Dist: wheel ; extra == 'dev'
